django_case_insensitive_field.py
django_case_insensitive_field-1.0.7.dist-info/LICENSE
django_case_insensitive_field-1.0.7.dist-info/METADATA
django_case_insensitive_field-1.0.7.dist-info/WHEEL
django_case_insensitive_field-1.0.7.dist-info/top_level.txt
django_case_insensitive_field-1.0.7.dist-info/RECORD
