Metadata-Version: 2.1
Name: django_case_insensitive_field
Version: 1.0.7
Summary: Django Case Insensitive Field is used to make Django Model Field case insensitive - by default Django can't do this.
Home-page: https://github.com/iamoracle/django_case_insensitive_field
Download-URL: https://github.com/iamoracle/django_case_insensitive_field/archive/refs/tags/v1.0.7.tar.gz
Author: iamoracle
Author-email: officialbilas@gmail.com
License: MIT
Keywords: Django,Case Insensitive,Field,How to make Django Field,make django case insensitive
Classifier: Development Status :: 3 - Alpha
Classifier: Intended Audience :: Developers
Classifier: Topic :: Software Development :: Build Tools
Classifier: License :: OSI Approved :: MIT License
Classifier: Programming Language :: Python :: 3
Classifier: Programming Language :: Python :: 3.4
Classifier: Programming Language :: Python :: 3.5
Classifier: Programming Language :: Python :: 3.6
Classifier: Programming Language :: Python :: 3.7
Classifier: Programming Language :: Python :: 3.8
Classifier: Programming Language :: Python :: 3.9
Classifier: Programming Language :: Python :: 3.10
License-File: LICENSE
